backspaceAlpha/__init__.py
backspaceAlpha/examples/BuyAndHoldSPYStrategy.py
backspaceAlpha/examples/MeanReversionStrategy.py
backspaceAlpha/examples/PairsTradingStrategy.py
backspaceAlpha/examples/SMAMomentumStrategy.py
backspaceAlpha/examples/__init__.py
backspaceAlpha/framework/__init__.py
backspaceAlpha/framework/backtest.py
backspaceAlpha/framework/broker.py
backspaceAlpha/framework/loader.py
backspaceAlpha/framework/strategy.py
backspaceAlpha/functions/RollingDrawdown.py
backspaceAlpha/functions/RollingSharpeRatio.py
backspaceAlpha/functions/__init__.py
backspacealpha-0.2.3.dist-info/licenses/LICENSE
backspacealpha-0.2.3.dist-info/METADATA
backspacealpha-0.2.3.dist-info/WHEEL
backspacealpha-0.2.3.dist-info/top_level.txt
backspacealpha-0.2.3.dist-info/RECORD
