Metadata-Version: 2.4
Name: backspaceAlpha
Version: 0.2.3
Summary: A simple backtesting framework to quickly and easily optimise strategies
Author-email: Aadi Deepchand <aadideepchand8254@gmail.com>
License-Expression: LicenseRef-BackspaceAlpha
Project-URL: Homepage, https://github.com/aadideepchand25/backspaceAlpha
Requires-Python: >=3.8
License-File: LICENSE
Requires-Dist: matplotlib
Requires-Dist: tqdm
Requires-Dist: yfinance
Requires-Dist: numpy
Requires-Dist: pandas
Dynamic: license-file
